hypermodern_python_lucasmbastos/__init__.py
hypermodern_python_lucasmbastos/console.py
hypermodern_python_lucasmbastos/wikipedia.py
hypermodern_python_lucasmbastos-0.1.0.dist-info/entry_points.txt
hypermodern_python_lucasmbastos-0.1.0.dist-info/LICENSE
hypermodern_python_lucasmbastos-0.1.0.dist-info/WHEEL
hypermodern_python_lucasmbastos-0.1.0.dist-info/METADATA
hypermodern_python_lucasmbastos-0.1.0.dist-info/RECORD
